bf_tools/bf_info.py
bf_tools-0.7.0.dist-info/entry_points.txt
bf_tools-0.7.0.dist-info/WHEEL
bf_tools-0.7.0.dist-info/METADATA
bf_tools-0.7.0.dist-info/RECORD
